buildingpy/__init__.py
buildingpy/bp_single_file.py
buildingpy/buildingpy.py
buildingpy-0.0.5.dist-info/licenses/LICENSE
buildingpy-0.0.5.dist-info/METADATA
buildingpy-0.0.5.dist-info/WHEEL
buildingpy-0.0.5.dist-info/top_level.txt
buildingpy-0.0.5.dist-info/RECORD
