Metadata-Version: 2.4
Name: buildingpy
Version: 0.0.5
Summary: BIM for python
Home-page: https://github.com/3BMLabs/building.py
Author: 3BM
Author-email: info@3bm.co.nl
License-File: LICENSE
Dynamic: author
Dynamic: author-email
Dynamic: description
Dynamic: home-page
Dynamic: license-file
Dynamic: summary
